odoo/addons/sale_timesheet_lock_invoiced/README.rst
odoo/addons/sale_timesheet_lock_invoiced/__init__.py
odoo/addons/sale_timesheet_lock_invoiced/__manifest__.py
odoo/addons/sale_timesheet_lock_invoiced/i18n/fr.po
odoo/addons/sale_timesheet_lock_invoiced/i18n/sale_timesheet_lock_invoiced.pot
odoo/addons/sale_timesheet_lock_invoiced/models/__init__.py
odoo/addons/sale_timesheet_lock_invoiced/models/account_analytic_line.py
odoo/addons/sale_timesheet_lock_invoiced/static/description/icon.png
odoo/addons/sale_timesheet_lock_invoiced/tests/__init__.py
odoo/addons/sale_timesheet_lock_invoiced/tests/test_sale_timesheet_lock_invoiced.py
odoo11_addon_sale_timesheet_lock_invoiced-11.0.1.0.1.dist-info/METADATA
odoo11_addon_sale_timesheet_lock_invoiced-11.0.1.0.1.dist-info/WHEEL
odoo11_addon_sale_timesheet_lock_invoiced-11.0.1.0.1.dist-info/top_level.txt
odoo11_addon_sale_timesheet_lock_invoiced-11.0.1.0.1.dist-info/RECORD
